[
    {
        "id": "123456789",
        "calibration_id": "1",
        "start_date": "2019-06-28T10:55:17.561547",
        "end_date": "2019-06-28T10:55:17.561547",
        "play_time_in_sec": "123",
        "reps_grsp": "123",
        "reps_h": "123",
        "reps_v": "123",
        "game_type": "Pong",
        "game_score": 1,
        "game_score_tag": "123",
        "game_status": "Finish",
        "gameplay_raw_data": "",
        "game_start_raw_data": "",
        "game_end_raw_data": "",
        "log_file_name": "file_name.json",
        "user_id": "123"
    },
    {
        "id": "1",
        "calibration_id": "1",
        "start_date": "2019-06-28T10:55:17.561547",
        "end_date": "2019-06-28T10:55:17.561547",
        "play_time_in_sec": "123",
        "reps_grsp": "123",
        "reps_h": "123",
        "reps_v": "123",
        "game_type": "Pong",
        "game_score": 2,
        "game_score_tag": "123",
        "game_status": "Finish",
        "gameplay_raw_data": "",
        "game_start_raw_data": "",
        "game_end_raw_data": "",
        "log_file_name": "file_name.json",
        "user_id": "124"
    },
    {
        "id": "2",
        "calibration_id": "1",
        "start_date": "2019-06-28T10:55:17.561547",
        "end_date": "2019-06-28T10:55:17.561547",
        "play_time_in_sec": "123",
        "reps_grsp": "123",
        "reps_h": "123",
        "reps_v": "123",
        "game_type": "Pong",
        "game_score": 3,
        "game_score_tag": "123",
        "game_status": "Finish",
        "gameplay_raw_data": "",
        "game_start_raw_data": "",
        "game_end_raw_data": "",
        "log_file_name": "file_name.json",
        "user_id": "125"
    },
    {
        "id": "3",
        "calibration_id": "1",
        "start_date": "2019-06-28T10:55:17.561547",
        "end_date": "2019-06-28T10:55:17.561547",
        "play_time_in_sec": "123",
        "reps_grsp": "123",
        "reps_h": "123",
        "reps_v": "123",
        "game_type": "Pong",
        "game_score": 4,
        "game_score_tag": "123",
        "game_status": "Finish",
        "gameplay_raw_data": "",
        "game_start_raw_data": "",
        "game_end_raw_data": "",
        "log_file_name": "file_name.json",
        "user_id": "125"
    },
    {
        "id": "4",
        "calibration_id": "1",
        "start_date": "2019-06-28T10:55:17.561547",
        "end_date": "2019-06-28T10:55:17.561547",
        "play_time_in_sec": "123",
        "reps_grsp": "123",
        "reps_h": "123",
        "reps_v": "123",
        "game_type": "SpaceShooter",
        "game_score": 5,
        "game_score_tag": "123",
        "game_status": "Finish",
        "gameplay_raw_data": "",
        "game_start_raw_data": "",
        "game_end_raw_data": "",
        "log_file_name": "file_name.json",
        "user_id": "123"
    },
    {
        "id": "5",
        "calibration_id": "1",
        "start_date": "2019-06-28T10:55:17.561547",
        "end_date": "2019-06-28T10:55:17.561547",
        "play_time_in_sec": "123",
        "reps_grsp": "123",
        "reps_h": "123",
        "reps_v": "123",
        "game_type": "SpaceShooter",
        "game_score": 6,
        "game_score_tag": "123",
        "game_status": "Finish",
        "gameplay_raw_data": "",
        "game_start_raw_data": "",
        "game_end_raw_data": "",
        "log_file_name": "file_name.json",
        "user_id": "124"
    },
    {
        "id": "6",
        "calibration_id": "1",
        "start_date": "2019-06-28T10:55:17.561547",
        "end_date": "2019-06-28T10:55:17.561547",
        "play_time_in_sec": "123",
        "reps_grsp": "123",
        "reps_h": "123",
        "reps_v": "123",
        "game_type": "SpaceShooter",
        "game_score": 7,
        "game_score_tag": "123",
        "game_status": "Finish",
        "gameplay_raw_data": "",
        "game_start_raw_data": "",
        "game_end_raw_data": "",
        "log_file_name": "file_name.json",
        "user_id": "125"
    },
    {
        "id": "7",
        "calibration_id": "1",
        "start_date": "2019-06-28T10:55:17.561547",
        "end_date": "2019-06-28T10:55:17.561547",
        "play_time_in_sec": "123",
        "reps_grsp": "123",
        "reps_h": "123",
        "reps_v": "123",
        "game_type": "SpaceShooter",
        "game_score": 8,
        "game_score_tag": "123",
        "game_status": "Finish",
        "gameplay_raw_data": "",
        "game_start_raw_data": "",
        "game_end_raw_data": "",
        "log_file_name": "file_name.json",
        "user_id": "125"
    },
    {
        "id": "8",
        "calibration_id": "1",
        "start_date": "2019-06-28T10:55:17.561547",
        "end_date": "2019-06-28T10:55:17.561547",
        "play_time_in_sec": "123",
        "reps_grsp": "123",
        "reps_h": "123",
        "reps_v": "123",
        "game_type": "RehabDiver",
        "game_score": 9,
        "game_score_tag": "123",
        "game_status": "Finish",
        "gameplay_raw_data": "",
        "game_start_raw_data": "",
        "game_end_raw_data": "",
        "log_file_name": "file_name.json",
        "user_id": "123"
    },
    {
        "id": "9",
        "calibration_id": "1",
        "start_date": "2019-06-28T10:55:17.561547",
        "end_date": "2019-06-28T10:55:17.561547",
        "play_time_in_sec": "123",
        "reps_grsp": "123",
        "reps_h": "123",
        "reps_v": "123",
        "game_type": "RehabDiver",
        "game_score": 10,
        "game_score_tag": "123",
        "game_status": "Finish",
        "gameplay_raw_data": "",
        "game_start_raw_data": "",
        "game_end_raw_data": "",
        "log_file_name": "file_name.json",
        "user_id": "124"
    },
    {
        "id": "10",
        "calibration_id": "1",
        "start_date": "2019-06-28T10:55:17.561547",
        "end_date": "2019-06-28T10:55:17.561547",
        "play_time_in_sec": "123",
        "reps_grsp": "123",
        "reps_h": "123",
        "reps_v": "123",
        "game_type": "RehabDiver",
        "game_score": 11,
        "game_score_tag": "123",
        "game_status": "Finish",
        "gameplay_raw_data": "",
        "game_start_raw_data": "",
        "game_end_raw_data": "",
        "log_file_name": "file_name.json",
        "user_id": "125"
    },
    {
        "id": "11",
        "calibration_id": "1",
        "start_date": "2019-06-28T10:55:17.561547",
        "end_date": "2019-06-28T10:55:17.561547",
        "play_time_in_sec": "123",
        "reps_grsp": "123",
        "reps_h": "123",
        "reps_v": "123",
        "game_type": "RehabDiver",
        "game_score": 12,
        "game_score_tag": "123",
        "game_status": "Finish",
        "gameplay_raw_data": "",
        "game_start_raw_data": "",
        "game_end_raw_data": "",
        "log_file_name": "file_name.json",
        "user_id": "125"
    },
    {
        "id": "12",
        "calibration_id": "1",
        "start_date": "2019-06-28T10:55:17.561547",
        "end_date": "2019-06-28T10:55:17.561547",
        "play_time_in_sec": "123",
        "reps_grsp": "123",
        "reps_h": "123",
        "reps_v": "123",
        "game_type": "PacMan",
        "game_score": 13,
        "game_score_tag": "123",
        "game_status": "Finish",
        "gameplay_raw_data": "",
        "game_start_raw_data": "",
        "game_end_raw_data": "",
        "log_file_name": "file_name.json",
        "user_id": "123"
    },
    {
        "id": "13",
        "calibration_id": "1",
        "start_date": "2019-06-28T10:55:17.561547",
        "end_date": "2019-06-28T10:55:17.561547",
        "play_time_in_sec": "123",
        "reps_grsp": "123",
        "reps_h": "123",
        "reps_v": "123",
        "game_type": "PacMan",
        "game_score": 14,
        "game_score_tag": "123",
        "game_status": "Finish",
        "gameplay_raw_data": "",
        "game_start_raw_data": "",
        "game_end_raw_data": "",
        "log_file_name": "file_name.json",
        "user_id": "124"
    },
    {
        "id": "14",
        "calibration_id": "1",
        "start_date": "2019-06-28T10:55:17.561547",
        "end_date": "2019-06-28T10:55:17.561547",
        "play_time_in_sec": "123",
        "reps_grsp": "123",
        "reps_h": "123",
        "reps_v": "123",
        "game_type": "PacMan",
        "game_score": 15,
        "game_score_tag": "123",
        "game_status": "Finish",
        "gameplay_raw_data": "",
        "game_start_raw_data": "",
        "game_end_raw_data": "",
        "log_file_name": "file_name.json",
        "user_id": "125"
    },
    {
        "id": "15",
        "calibration_id": "1",
        "start_date": "2019-06-28T10:55:17.561547",
        "end_date": "2019-06-28T10:55:17.561547",
        "play_time_in_sec": "123",
        "reps_grsp": "123",
        "reps_h": "123",
        "reps_v": "123",
        "game_type": "PacMan",
        "game_score": 16,
        "game_score_tag": "123",
        "game_status": "Finish",
        "gameplay_raw_data": "",
        "game_start_raw_data": "",
        "game_end_raw_data": "",
        "log_file_name": "file_name.json",
        "user_id": "125"
    },
    {
        "id": "16",
        "calibration_id": "1",
        "start_date": "2019-06-28T10:55:17.561547",
        "end_date": "2019-06-28T10:55:17.561547",
        "play_time_in_sec": "123",
        "reps_grsp": "123",
        "reps_h": "123",
        "reps_v": "123",
        "game_type": "HolidaysJogging",
        "game_score": 17,
        "game_score_tag": "123",
        "game_status": "Finish",
        "gameplay_raw_data": "",
        "game_start_raw_data": "",
        "game_end_raw_data": "",
        "log_file_name": "file_name.json",
        "user_id": "123"
    },
    {
        "id": "17",
        "calibration_id": "1",
        "start_date": "2019-06-28T10:55:17.561547",
        "end_date": "2019-06-28T10:55:17.561547",
        "play_time_in_sec": "123",
        "reps_grsp": "123",
        "reps_h": "123",
        "reps_v": "123",
        "game_type": "HolidaysJogging",
        "game_score": 18,
        "game_score_tag": "123",
        "game_status": "Finish",
        "gameplay_raw_data": "",
        "game_start_raw_data": "",
        "game_end_raw_data": "",
        "log_file_name": "file_name.json",
        "user_id": "124"
    },
    {
        "id": "18",
        "calibration_id": "1",
        "start_date": "2019-06-28T10:55:17.561547",
        "end_date": "2019-06-28T10:55:17.561547",
        "play_time_in_sec": "123",
        "reps_grsp": "123",
        "reps_h": "123",
        "reps_v": "123",
        "game_type": "HolidaysJogging",
        "game_score": 19,
        "game_score_tag": "123",
        "game_status": "Finish",
        "gameplay_raw_data": "",
        "game_start_raw_data": "",
        "game_end_raw_data": "",
        "log_file_name": "file_name.json",
        "user_id": "125"
    },
    {
        "id": "19",
        "calibration_id": "1",
        "start_date": "2019-06-28T10:55:17.561547",
        "end_date": "2019-06-28T10:55:17.561547",
        "play_time_in_sec": "123",
        "reps_grsp": "123",
        "reps_h": "123",
        "reps_v": "123",
        "game_type": "HolidaysJogging",
        "game_score": 20,
        "game_score_tag": "123",
        "game_status": "Finish",
        "gameplay_raw_data": "",
        "game_start_raw_data": "",
        "game_end_raw_data": "",
        "log_file_name": "file_name.json",
        "user_id": "125"
    }
]